MANIFEST.in
README.md
cuda_setup.py
pyproject.toml
requirements.txt
setup.py
3rd/json11/.git
3rd/json11/.gitignore
3rd/json11/CMakeLists.txt
3rd/json11/LICENSE.txt
3rd/json11/Makefile
3rd/json11/README.md
3rd/json11/json11.cpp
3rd/json11/json11.hpp
3rd/json11/json11.pc.in
3rd/json11/test.cpp
3rd/spdlog/.clang-format
3rd/spdlog/.clang-tidy
3rd/spdlog/.git
3rd/spdlog/.gitattributes
3rd/spdlog/.gitignore
3rd/spdlog/.travis.yml
3rd/spdlog/CMakeLists.txt
3rd/spdlog/INSTALL
3rd/spdlog/LICENSE
3rd/spdlog/README.md
3rd/spdlog/appveyor.yml
3rd/spdlog/bench/CMakeLists.txt
3rd/spdlog/bench/async_bench.cpp
3rd/spdlog/bench/bench.cpp
3rd/spdlog/bench/formatter-bench.cpp
3rd/spdlog/bench/latency.cpp
3rd/spdlog/bench/utils.h
3rd/spdlog/cmake/ide.cmake
3rd/spdlog/cmake/pch.h.in
3rd/spdlog/cmake/spdlog.pc.in
3rd/spdlog/cmake/spdlogCPack.cmake
3rd/spdlog/cmake/spdlogConfig.cmake.in
3rd/spdlog/cmake/utils.cmake
3rd/spdlog/cmake/version.rc.in
3rd/spdlog/example/CMakeLists.txt
3rd/spdlog/example/example.cpp
3rd/spdlog/include/spdlog/async.h
3rd/spdlog/include/spdlog/async_logger-inl.h
3rd/spdlog/include/spdlog/async_logger.h
3rd/spdlog/include/spdlog/common-inl.h
3rd/spdlog/include/spdlog/common.h
3rd/spdlog/include/spdlog/formatter.h
3rd/spdlog/include/spdlog/fwd.h
3rd/spdlog/include/spdlog/logger-inl.h
3rd/spdlog/include/spdlog/logger.h
3rd/spdlog/include/spdlog/pattern_formatter-inl.h
3rd/spdlog/include/spdlog/pattern_formatter.h
3rd/spdlog/include/spdlog/spdlog-inl.h
3rd/spdlog/include/spdlog/spdlog.h
3rd/spdlog/include/spdlog/stopwatch.h
3rd/spdlog/include/spdlog/tweakme.h
3rd/spdlog/include/spdlog/version.h
3rd/spdlog/include/spdlog/cfg/argv.h
3rd/spdlog/include/spdlog/cfg/env.h
3rd/spdlog/include/spdlog/cfg/helpers-inl.h
3rd/spdlog/include/spdlog/cfg/helpers.h
3rd/spdlog/include/spdlog/details/backtracer-inl.h
3rd/spdlog/include/spdlog/details/backtracer.h
3rd/spdlog/include/spdlog/details/circular_q.h
3rd/spdlog/include/spdlog/details/console_globals.h
cuhnsw.egg-info/PKG-INFO
cuhnsw.egg-info/SOURCES.txt
cuhnsw.egg-info/dependency_links.txt
cuhnsw.egg-info/entry_points.txt
cuhnsw.egg-info/requires.txt
cuhnsw.egg-info/top_level.txt